<HBProfile creator="Headshother0" version="LOW GEAR">

    <Name>Headshother0 85-90</Name>
    <MinLevel>78</MinLevel>
    <MaxLevel>91</MaxLevel>
   
    <MinDurability>0.3</MinDurability>
    <MinFreeBagSlots>1</MinFreeBagSlots>
   
   	<SellGrey>True</SellGrey>
   	<SellWhite>True</SellWhite>
	<SellGreen>False</SellGreen>

	<MailWhite>True</MailWhite>
	<MailGreen>True</MailGreen>
	<MailBlue>True</MailBlue>
	<MailPurple>True</MailPurple>
	
    <Vendors>
<Vendor Name="Vendor Jambeezi" Entry="59583" Type="Repair" X="-150.9885" Y="509.9315" Z="207.1227" />
<Vendor Name="Den Den" Entry="64319" Type="Food" X="-222.6754" Y="525.4271" Z="190.8914" />
	</Vendors>
   
    <Mailboxes>
<Mailbox X="-209.7626" Y="496.6556" Z="187.2196" />
	</Mailboxes>

    <GrindArea>
		<TargetMinLevel>80</TargetMinLevel>
		<TargetMaxLevel>89</TargetMaxLevel>
<Factions>14 56462</Factions>
		<LootRadius>10</LootRadius>
<MaxDistance>10</MaxDistance>
<Hotspots>
<Hotspot X="360.3278" Y="-727.0975" Z="233.4561" />
<Hotspot X="332.365" Y="-715.4498" Z="232.596" />
<Hotspot X="343.9349" Y="-691.9215" Z="237.6765" />
<Hotspot X="342.4123" Y="-671.0824" Z="239.2378" />
        </Hotspots>
<Blackspots>
	<Blackspot X="367.1612" Y="-699.0712" Z="220.4356" Radius="17.2244" Height="14.49007" />
</Blackspots>
    </GrindArea>

<AvoidMobs> 
<Mob Name="Thieving Plainshawk" Entry="56034"/>
<Mob Name="Monstrous Plainshawk" Entry="59641"/>
</AvoidMobs>

</HBProfile>
