<?xml version="1.0" encoding="utf-8"?>
<FlightNodes>
  <Node name="Frostwallgarnison, Frostfeuergrat" continent="1116" master="79407" x="5578.94" y="4564.84" z="136.874">
    <Connections>
      <Connection name="Anhöhe der Exilanten, Schattenmondtal" />
      <Connection name="Wor'gol, Frostfeuergrat" />
      <Connection name="Speerspießerfestung, Frostfeuergrat" />
      <Connection name="Blutschlägermine, Frostfeuergrat" />
      <Connection name="Steinzahnposten, Frostfeuergrat" />
      <Connection name="Donnerpass, Frostfeuergrat" />
      <Connection name="Dunkelspeerspalte, Frostfeuergrat" />
      <Connection name="Kriegsspeer, Ashran" />
      <Connection name="Zangarra, Talador" />
      <Connection name="Frostwolfwarte, Talador" />
      <Connection name="Wildwacht, Gorgrond" />
      <Connection name="Vol'jins Stolz, Talador" />
      <Connection name="Durotans Brückenkopf, Talador" />
      <Connection name="Shattrath, Talador" />
      <Connection name="Platz der Vergelter, Talador" />
      <Connection name="Zuflucht des Exarchen, Talador" />
      <Connection name="Terokkarzuflucht, Talador" />
      <Connection name="Socrethars Klippe, Schattenmondtal" />
      <Connection name="Axtfall, Spitzen von Arak" />
      <Connection name="Ring der Prüfung, Nagrand" />
      <Connection name="Thron der Elemente, Nagrand" />
      <Connection name="Wor'var, Nagrand" />
      <Connection name="Uferposten, Nagrand" />
      <Connection name="Terokkversteck, Spitzen von Arak" />
      <Connection name="Klauenwacht, Spitzen von Arak" />
      <Connection name="Werkstatt Quetschpfeif, Spitzen von Arak" />
      <Connection name="Bastionsklippe, Gorgrond" />
      <Connection name="Apexisausgrabung, Spitzen von Arak" />
      <Connection name="Immermornquellen, Gorgrond" />
      <Connection name="Krähenwinkel, Spitzen von Arak" />
      <Connection name="Brecherkuppe, Gorgrond" />
      <Connection name="Eisendocks, Gorgrond" />
      <Connection name="Nachtflutnest, Schattenmondtal" />
      <Connection name="Horizontklippe, Gorgrond" />
      <Connection name="Wolfswehr, Frostfeuergrat" />
      <Connection name="Die Immergrüne Wildnis, Gorgrond" />
      <Connection name="Akeetas Hütte, Schattenmondtal" />
      <Connection name="Rilzits Stützpunkt, Nagrand" />
      <Connection name="Niveks Aussichtspunkt, Nagrand" />
      <Connection name="Joz' Rylaks, Nagrand" />
      <Connection name="Die Immergrüne Aussicht, Gorgrond" />
    </Connections>
  </Node>
  <Node name="Anhöhe der Exilanten, Schattenmondtal" continent="1116" x="1526.38" y="-788.891" z="43.0647">
    <Connections>
      <Connection name="Frostwallgarnison, Frostfeuergrat" />
    </Connections>
  </Node>
  <Node name="Wor'gol, Frostfeuergrat" continent="1116" x="5988.68" y="6180.86" z="71.1247">
    <Connections>
      <Connection name="Frostwallgarnison, Frostfeuergrat" />
    </Connections>
  </Node>
  <Node name="Speerspießerfestung, Frostfeuergrat" continent="1116" x="6754.56" y="6012.54" z="250.034">
    <Connections>
      <Connection name="Frostwallgarnison, Frostfeuergrat" />
    </Connections>
  </Node>
  <Node name="Throm'var, Frostfeuergrat" continent="1116" x="7879.57" y="5560.17" z="111.117">
    <Connections />
  </Node>
  <Node name="Blutschlägermine, Frostfeuergrat" continent="1116" x="7399.45" y="4358.41" z="126.406">
    <Connections>
      <Connection name="Frostwallgarnison, Frostfeuergrat" />
    </Connections>
  </Node>
  <Node name="Steinzahnposten, Frostfeuergrat" continent="1116" x="6157.56" y="5052.44" z="134.315">
    <Connections>
      <Connection name="Frostwallgarnison, Frostfeuergrat" />
    </Connections>
  </Node>
  <Node name="Donnerpass, Frostfeuergrat" continent="1116" x="5789.57" y="2394.89" z="201.354">
    <Connections>
      <Connection name="Frostwallgarnison, Frostfeuergrat" />
    </Connections>
  </Node>
  <Node name="Dunkelspeerspalte, Frostfeuergrat" continent="1116" x="6600" y="4342.55" z="91.1115">
    <Connections>
      <Connection name="Frostwallgarnison, Frostfeuergrat" />
    </Connections>
  </Node>
  <Node name="Kriegsspeer, Ashran" continent="1116" x="5356.23" y="-3942.24" z="32.7331">
    <Connections>
      <Connection name="Frostwallgarnison, Frostfeuergrat" />
    </Connections>
  </Node>
  <Node name="Zangarra, Talador" continent="1116" x="3418.78" y="1040.15" z="178.085">
    <Connections>
      <Connection name="Frostwallgarnison, Frostfeuergrat" />
    </Connections>
  </Node>
  <Node name="Frostwolfwarte, Talador" continent="1116" x="4008.86" y="2166.87" z="119.805">
    <Connections>
      <Connection name="Frostwallgarnison, Frostfeuergrat" />
    </Connections>
  </Node>
  <Node name="Wildwacht, Gorgrond" continent="1116" x="5815.51" y="1304.34" z="109.125">
    <Connections>
      <Connection name="Frostwallgarnison, Frostfeuergrat" />
    </Connections>
  </Node>
  <Node name="Vol'jins Stolz, Talador" continent="1116" x="3258.83" y="1609.27" z="162.396">
    <Connections>
      <Connection name="Frostwallgarnison, Frostfeuergrat" />
    </Connections>
  </Node>
  <Node name="Durotans Brückenkopf, Talador" continent="1116" x="2808.79" y="2525.74" z="120.939">
    <Connections>
      <Connection name="Frostwallgarnison, Frostfeuergrat" />
    </Connections>
  </Node>
  <Node name="Shattrath, Talador" continent="1116" x="2727.16" y="2777" z="242.933">
    <Connections>
      <Connection name="Frostwallgarnison, Frostfeuergrat" />
    </Connections>
  </Node>
  <Node name="Platz der Vergelter, Talador" continent="1116" x="1378.4" y="3318.52" z="138.134">
    <Connections>
      <Connection name="Frostwallgarnison, Frostfeuergrat" />
    </Connections>
  </Node>
  <Node name="Zuflucht des Exarchen, Talador" continent="1116" x="1731.09" y="2581.53" z="133.659">
    <Connections>
      <Connection name="Frostwallgarnison, Frostfeuergrat" />
    </Connections>
  </Node>
  <Node name="Terokkarzuflucht, Talador" continent="1116" x="2158.65" y="1634.47" z="131.817">
    <Connections>
      <Connection name="Frostwallgarnison, Frostfeuergrat" />
    </Connections>
  </Node>
  <Node name="Socrethars Klippe, Schattenmondtal" continent="1116" x="-799.674" y="-671.424" z="107.102">
    <Connections>
      <Connection name="Frostwallgarnison, Frostfeuergrat" />
    </Connections>
  </Node>
  <Node name="Axtfall, Spitzen von Arak" continent="1116" x="-368.201" y="2285.55" z="33.983">
    <Connections>
      <Connection name="Frostwallgarnison, Frostfeuergrat" />
    </Connections>
  </Node>
  <Node name="Ring der Prüfung, Nagrand" continent="1116" x="3040.78" y="4783.08" z="128.275">
    <Connections>
      <Connection name="Frostwallgarnison, Frostfeuergrat" />
    </Connections>
  </Node>
  <Node name="Thron der Elemente, Nagrand" continent="1116" x="3918.79" y="5131.45" z="62.728">
    <Connections>
      <Connection name="Frostwallgarnison, Frostfeuergrat" />
    </Connections>
  </Node>
  <Node name="Wor'var, Nagrand" continent="1116" x="3235.73" y="4584.55" z="144.607">
    <Connections>
      <Connection name="Frostwallgarnison, Frostfeuergrat" />
    </Connections>
  </Node>
  <Node name="Uferposten, Nagrand" continent="1116" x="3102.81" y="6500.38" z="17.6317">
    <Connections>
      <Connection name="Frostwallgarnison, Frostfeuergrat" />
    </Connections>
  </Node>
  <Node name="Terokkversteck, Spitzen von Arak" continent="1116" x="-398.988" y="1880.12" z="51.2684">
    <Connections>
      <Connection name="Frostwallgarnison, Frostfeuergrat" />
    </Connections>
  </Node>
  <Node name="Klauenwacht, Spitzen von Arak" continent="1116" x="-335.451" y="926.622" z="75.2153">
    <Connections>
      <Connection name="Frostwallgarnison, Frostfeuergrat" />
    </Connections>
  </Node>
  <Node name="Werkstatt Quetschpfeif, Spitzen von Arak" continent="1116" x="-1579.14" y="993.09" z="8.08963">
    <Connections>
      <Connection name="Frostwallgarnison, Frostfeuergrat" />
    </Connections>
  </Node>
  <Node name="Bastionsklippe, Gorgrond" continent="1116" x="4641.62" y="1188.07" z="137.088">
    <Connections>
      <Connection name="Frostwallgarnison, Frostfeuergrat" />
    </Connections>
  </Node>
  <Node name="Apexisausgrabung, Spitzen von Arak" continent="1116" x="387.542" y="2442.73" z="19.3169">
    <Connections>
      <Connection name="Frostwallgarnison, Frostfeuergrat" />
    </Connections>
  </Node>
  <Node name="Immermornquellen, Gorgrond" continent="1116" x="4837.63" y="1687.55" z="148.983">
    <Connections>
      <Connection name="Frostwallgarnison, Frostfeuergrat" />
    </Connections>
  </Node>
  <Node name="Krähenwinkel, Spitzen von Arak" continent="1116" x="128.615" y="1544.63" z="-1.72825">
    <Connections>
      <Connection name="Frostwallgarnison, Frostfeuergrat" />
    </Connections>
  </Node>
  <Node name="Brecherkuppe, Gorgrond" continent="1116" x="6593.43" y="1316.04" z="64.6343">
    <Connections>
      <Connection name="Frostwallgarnison, Frostfeuergrat" />
    </Connections>
  </Node>
  <Node name="Eisendocks, Gorgrond" continent="1116" x="8486.15" y="1544.24" z="78.8754">
    <Connections>
      <Connection name="Frostwallgarnison, Frostfeuergrat" />
    </Connections>
  </Node>
  <Node name="Nachtflutnest, Schattenmondtal" continent="1116" x="-974.125" y="-1739.3" z="2.99791">
    <Connections>
      <Connection name="Frostwallgarnison, Frostfeuergrat" />
    </Connections>
  </Node>
  <Node name="Horizontklippe, Gorgrond" continent="1116" x="7596.2" y="1829.05" z="79.0772">
    <Connections>
      <Connection name="Frostwallgarnison, Frostfeuergrat" />
    </Connections>
  </Node>
  <Node name="Wolfswehr, Frostfeuergrat" continent="1116" x="5830.86" y="3004.09" z="183.21">
    <Connections>
      <Connection name="Frostwallgarnison, Frostfeuergrat" />
    </Connections>
  </Node>
  <Node name="Die Immergrüne Wildnis, Gorgrond" continent="1116" x="7093.6" y="404.74" z="112.001">
    <Connections>
      <Connection name="Frostwallgarnison, Frostfeuergrat" />
    </Connections>
  </Node>
  <Node name="Akeetas Hütte, Schattenmondtal" continent="1116" x="676.424" y="701.439" z="113.96">
    <Connections>
      <Connection name="Frostwallgarnison, Frostfeuergrat" />
    </Connections>
  </Node>
  <Node name="Rilzits Stützpunkt, Nagrand" continent="1116" x="3761.26" y="6430.15" z="21.6669">
    <Connections>
      <Connection name="Frostwallgarnison, Frostfeuergrat" />
    </Connections>
  </Node>
  <Node name="Niveks Aussichtspunkt, Nagrand" continent="1116" x="2053.66" y="6507.39" z="32.264">
    <Connections>
      <Connection name="Frostwallgarnison, Frostfeuergrat" />
    </Connections>
  </Node>
  <Node name="Joz' Rylaks, Nagrand" continent="1116" x="3676.04" y="5776.19" z="45.4013">
    <Connections>
      <Connection name="Frostwallgarnison, Frostfeuergrat" />
    </Connections>
  </Node>
  <Node name="Die Immergrüne Aussicht, Gorgrond" continent="1116" x="8018.09" y="-560.49" z="154.967">
    <Connections>
      <Connection name="Frostwallgarnison, Frostfeuergrat" />
    </Connections>
  </Node>
</FlightNodes>