<?xml version="1.0" encoding="utf-8"?>
<THSettings>
  <AutoAoE>False</AutoAoE>
  <AutoDetectManualCast>False</AutoDetectManualCast>
  <AutoDetectManualCastMS>100</AutoDetectManualCastMS>
  <AntiMagicShell>True</AntiMagicShell>
  <AntiMagicShellHP>30</AntiMagicShellHP>
  <AntiMagicShellEnemy>False</AntiMagicShellEnemy>
  <AntiMagicShellEnemyHP>20</AntiMagicShellEnemyHP>
  <AntiMagicShellDebuff>True</AntiMagicShellDebuff>
  <AntiMagicShellDebuffNumber>10</AntiMagicShellDebuffNumber>
  <AntiMagicShellCaster>False</AntiMagicShellCaster>
  <AntiMagicShellCasterNumber>3</AntiMagicShellCasterNumber>
  <AntiMagicShellCC>False</AntiMagicShellCC>
  <AntiMagicZone>True</AntiMagicZone>
  <AntiMagicZoneHP>50</AntiMagicZoneHP>
  <AntiMagicZoneDebuff>True</AntiMagicZoneDebuff>
  <AntiMagicZoneDebuffNumber>3</AntiMagicZoneDebuffNumber>
  <AntiMagicZoneCaster>True</AntiMagicZoneCaster>
  <AntiMagicZoneCasterNumber>2</AntiMagicZoneCasterNumber>
  <AutoAttack>True</AutoAttack>
  <AutoBuff>True</AutoBuff>
  <AutoFace>True</AutoFace>
  <AutoUpdate>True</AutoUpdate>
  <AsphyxiateHelpFriend>True</AsphyxiateHelpFriend>
  <AsphyxiateHelpFriendHP>40</AsphyxiateHelpFriendHP>
  <AutoMove>False</AutoMove>
  <AutoPathofFrost>False</AutoPathofFrost>
  <AutoPrecence>True</AutoPrecence>
  <AutoRacial>True</AutoRacial>
  <AutoRaiseAlly>True</AutoRaiseAlly>
  <AutoTarget>True</AutoTarget>
  <AutoSetFocus>False</AutoSetFocus>
  <AutoTaunt>True</AutoTaunt>
  <AutoWriteLogDetail>False</AutoWriteLogDetail>
  <AttackASAP>True</AttackASAP>
  <AttackOOC>True</AttackOOC>
  <AutoWriteLog>True</AutoWriteLog>
  <BoneShield>True</BoneShield>
  <BloodBoil>True</BloodBoil>
  <BloodPresence>True</BloodPresence>
  <BloodPresenceHP>80</BloodPresenceHP>
  <BloodTap>True</BloodTap>
  <BreathofSindragosaCoodown>True</BreathofSindragosaCoodown>
  <BreathofSindragosaBurst>True</BreathofSindragosaBurst>
  <DispellMax>200</DispellMax>
  <DispellMin>100</DispellMin>
  <BurstKeyIndex>9</BurstKeyIndex>
  <BurstHP>30</BurstHP>
  <BurstString></BurstString>
  <ChainsofIce>True</ChainsofIce>
  <ChainsofIceMinDistance>8</ChainsofIceMinDistance>
  <ChainofIceMelee>True</ChainofIceMelee>
  <ChainofIceMeleeHP>90</ChainofIceMeleeHP>
  <ChargeInterrupt>True</ChargeInterrupt>
  <ChargeInterruptMS>2000</ChargeInterruptMS>
  <ChargeStunEnemy>True</ChargeStunEnemy>
  <ChargeStunEnemyHP>40</ChargeStunEnemyHP>
  <ChargeStunFriend>True</ChargeStunFriend>
  <ChargeStunFriendHP>40</ChargeStunFriendHP>
  <ControlUndead>False</ControlUndead>
  <DancingRuneWeapon>True</DancingRuneWeapon>
  <DancingRuneWeaponHP>50</DancingRuneWeaponHP>
  <DarkSimulacrumon>True</DarkSimulacrumon>
  <DarkSimulacrumonCast>False</DarkSimulacrumonCast>
  <DarkSimulacrumonCooldown>True</DarkSimulacrumonCooldown>
  <DarkSimulacrumonAuto>True</DarkSimulacrumonAuto>
  <DarkTransformation>True</DarkTransformation>
  <DarkTransformationPercentIncrease>0</DarkTransformationPercentIncrease>
  <DeathandDecay>True</DeathandDecay>
  <DeathandDecaySnare>True</DeathandDecaySnare>
  <DeathCoil>True</DeathCoil>
  <DeathCoilHelpFriend>True</DeathCoilHelpFriend>
  <DeathCoilHelpFriendHP>90</DeathCoilHelpFriendHP>
  <DeathCoilHealPet>True</DeathCoilHealPet>
  <DeathCoilHealPetHP>80</DeathCoilHealPetHP>
  <DeathGrip>False</DeathGrip>
  <DeathGripMinDistance>15</DeathGripMinDistance>
  <DeathGripMelee>True</DeathGripMelee>
  <DeathGripMeleeHP>80</DeathGripMeleeHP>
  <DeathPact>True</DeathPact>
  <DeathPactHP>50</DeathPactHP>
  <DeathsAdvance>True</DeathsAdvance>
  <DeathGripInterrupt>True</DeathGripInterrupt>
  <DeathStrikeBloodEnable>True</DeathStrikeBloodEnable>
  <DeathStrike>True</DeathStrike>
  <DeathStrikeHP>99</DeathStrikeHP>
  <Defile>True</Defile>
  <DesecratedGround>True</DesecratedGround>
  <DesecratedGroundDebuffMinDuration>3000</DesecratedGroundDebuffMinDuration>
  <DoNotHealAbove>95</DoNotHealAbove>
  <EmpowerRuneWeaponCooldown>False</EmpowerRuneWeaponCooldown>
  <EmpowerRuneWeaponBurst>True</EmpowerRuneWeaponBurst>
  <FesteringStrike>True</FesteringStrike>
  <FileandSettingCheckLast>0</FileandSettingCheckLast>
  <FlagReturnorPickup>True</FlagReturnorPickup>
  <Follow>True</Follow>
  <FollowDistance>50</FollowDistance>
  <FrostPresence>True</FrostPresence>
  <FrostStrike>True</FrostStrike>
  <SummonGargoyleCooldown>False</SummonGargoyleCooldown>
  <SummonGargoyleBurst>True</SummonGargoyleBurst>
  <GnawInterrupt>True</GnawInterrupt>
  <GnawInterruptMS>2000</GnawInterruptMS>
  <GnawStunEnemy>True</GnawStunEnemy>
  <GnawStunEnemyHP>40</GnawStunEnemyHP>
  <GnawStunFriend>True</GnawStunFriend>
  <GnawStunFriendHP>40</GnawStunFriendHP>
  <GorefiendsGraspInterrupt>True</GorefiendsGraspInterrupt>
  <GorefiendsGraspInterruptMS>2000</GorefiendsGraspInterruptMS>
  <GorefiendsGraspAggro>True</GorefiendsGraspAggro>
  <GorefiendsGraspAggroMinDist>10</GorefiendsGraspAggroMinDist>
  <GorefiendsGraspKiter>True</GorefiendsGraspKiter>
  <GorefiendsGraspKiterMinDist>10</GorefiendsGraspKiterMinDist>
  <GorefiendsGraspMelee>True</GorefiendsGraspMelee>
  <GorefiendsGraspMeleeHP>40</GorefiendsGraspMeleeHP>
  <GorefiendsGraspAoE>True</GorefiendsGraspAoE>
  <GorefiendsGraspAoENumber>3</GorefiendsGraspAoENumber>
  <Conversion>True</Conversion>
  <ConversionHP>80</ConversionHP>
  <HealBalancing>0</HealBalancing>
  <HealthStone>True</HealthStone>
  <HealthStoneHP>40</HealthStoneHP>
  <HeartStrike>True</HeartStrike>
  <HornofWinter>True</HornofWinter>
  <HowlingBlast>True</HowlingBlast>
  <Huddle>True</Huddle>
  <HuddleHP>50</HuddleHP>
  <IceboundFortitude>True</IceboundFortitude>
  <IceboundFortitudeHP>40</IceboundFortitudeHP>
  <IceboundFortitudeStun>True</IceboundFortitudeStun>
  <IceboundFortitudeStunDuration>2000</IceboundFortitudeStunDuration>
  <IcyTouch>True</IcyTouch>
  <InterruptAll>True</InterruptAll>
  <InterruptTarget>False</InterruptTarget>
  <InterruptFocus>False</InterruptFocus>
  <InterruptMinTimeToInterrupt>400</InterruptMinTimeToInterrupt>
  <InterruptMinChannelSpells>300</InterruptMinChannelSpells>
  <InterruptMinPercent>30</InterruptMinPercent>
  <InterruptMaxPercent>70</InterruptMaxPercent>
  <LastSavedSpec>Blood</LastSavedSpec>
  <LastSavedMode></LastSavedMode>
  <LagTolerance>True</LagTolerance>
  <LeapRange>True</LeapRange>
  <LeapRangeDist>30</LeapRangeDist>
  <LichborneFear>True</LichborneFear>
  <LichborneFearDuration>3000</LichborneFearDuration>
  <LichborneHeal>True</LichborneHeal>
  <LichborneHealHP>40</LichborneHealHP>
  <MindFreezeInterrupt>True</MindFreezeInterrupt>
  <Obliterate>True</Obliterate>
  <Outbreak>True</Outbreak>
  <PauseToggleKeys></PauseToggleKeys>
  <PausePressedKeys></PausePressedKeys>
  <Pause>False</Pause>
  <Pestilence>True</Pestilence>
  <PetAttack>True</PetAttack>
  <PillarofFrostCooldown>True</PillarofFrostCooldown>
  <PillarofFrostBurst>True</PillarofFrostBurst>
  <PlagueLeech>True</PlagueLeech>
  <PlagueStrike>True</PlagueStrike>
  <PriorityHeal>75</PriorityHeal>
  <RaiseDeadUnholy>True</RaiseDeadUnholy>
  <RemorselessWinter>True</RemorselessWinter>
  <RemorselessWinterHP>50</RemorselessWinterHP>
  <RemorselessWinterEnemy>True</RemorselessWinterEnemy>
  <RemorselessWinterEnemyNumber>4</RemorselessWinterEnemyNumber>
  <RemorselessWinterDeathGrip>True</RemorselessWinterDeathGrip>
  <RemorselessWinterBurst>False</RemorselessWinterBurst>
  <RemorselessWinterEnemyLow>True</RemorselessWinterEnemyLow>
  <RemorselessWinterEnemyLowHP>50</RemorselessWinterEnemyLowHP>
  <RuneStrike>True</RuneStrike>
  <RuneTap>True</RuneTap>
  <RuneTapHP>50</RuneTapHP>
  <ScourgeStrike>True</ScourgeStrike>
  <Siphon>True</Siphon>
  <SiphonHP>70</SiphonHP>
  <SoulReaper>True</SoulReaper>
  <SoulReaperHP>35</SoulReaperHP>
  <SoulReaperLow>True</SoulReaperLow>
  <StrangulateInterrupt>True</StrangulateInterrupt>
  <StrangulateLow>False</StrangulateLow>
  <StrangulateLowHP>30</StrangulateLowHP>
  <Trinket1>0</Trinket1>
  <Trinket1HP>70</Trinket1HP>
  <Trinket2>4</Trinket2>
  <Trinket2HP>60</Trinket2HP>
  <UnholyBlight>True</UnholyBlight>
  <UnholyPresence>True</UnholyPresence>
  <UrgentHeal>40</UrgentHeal>
  <UseFood>True</UseFood>
  <UseFoodHP>60</UseFoodHP>
  <UsePauseKey>True</UsePauseKey>
  <VampiricBlood>True</VampiricBlood>
  <VampiricBloodHP>40</VampiricBloodHP>
</THSettings>