<?xml version="1.0" encoding="utf-8"?>
<FlightNodes>
  <Node name="Mondsturz, Schattenmondtal" continent="1116" master="81103" x="1866.56" y="219.467" z="77.5279">
    <Connections>
      <Connection name="Embaari, Schattenmondtal" />
      <Connection name="Zwielichtflur, Schattenmondtal" />
      <Connection name="Pfad des Lichts, Schattenmondtal" />
      <Connection name="Anhöhe der Exilanten, Schattenmondtal" />
      <Connection name="Sturmschild, Ashran" />
      <Connection name="Das Draakorium, Schattenmondtal" />
      <Connection name="Elodor, Schattenmondtal" />
      <Connection name="Wildwuchsbett, Gorgrond" />
      <Connection name="Hochpass, Gorgrond" />
    </Connections>
  </Node>
  <Node name="Embaari, Schattenmondtal" continent="1116" x="918.264" y="-792.361" z="-28.8338">
    <Connections>
      <Connection name="Mondsturz, Schattenmondtal" />
    </Connections>
  </Node>
  <Node name="Zwielichtflur, Schattenmondtal" continent="1116" x="195.236" y="-459.2" z="-3.95986">
    <Connections>
      <Connection name="Mondsturz, Schattenmondtal" />
    </Connections>
  </Node>
  <Node name="Pfad des Lichts, Schattenmondtal" continent="1116" x="602.698" y="-1710.45" z="26.4837">
    <Connections>
      <Connection name="Mondsturz, Schattenmondtal" />
    </Connections>
  </Node>
  <Node name="Anhöhe der Exilanten, Schattenmondtal" continent="1116" x="1526.38" y="-788.891" z="43.0647">
    <Connections>
      <Connection name="Mondsturz, Schattenmondtal" />
    </Connections>
  </Node>
  <Node name="Blutschlägermine, Frostfeuergrat" continent="1116" x="7399.45" y="4358.41" z="126.406">
    <Connections />
  </Node>
  <Node name="Sturmschild, Ashran" continent="1116" x="3685.15" y="-3840.47" z="44.9819">
    <Connections>
      <Connection name="Mondsturz, Schattenmondtal" />
    </Connections>
  </Node>
  <Node name="Zangarra, Talador" continent="1116" x="3418.78" y="1040.15" z="178.085">
    <Connections />
  </Node>
  <Node name="Fort Wrynn, Talador" continent="1116" x="3576.81" y="1669.4" z="172.792">
    <Connections />
  </Node>
  <Node name="Erlösungsanhöhe, Talador" continent="1116" x="3407.73" y="2062" z="160.398">
    <Connections />
  </Node>
  <Node name="Shattrath, Talador" continent="1116" x="2727.16" y="2777" z="242.933">
    <Connections />
  </Node>
  <Node name="Anachoretenrast, Talador" continent="1116" x="2171.82" y="1059.22" z="112.517">
    <Connections />
  </Node>
  <Node name="Platz der Vergelter, Talador" continent="1116" x="1378.4" y="3318.52" z="138.134">
    <Connections />
  </Node>
  <Node name="Zuflucht des Exarchen, Talador" continent="1116" x="1696.5" y="2561.35" z="133.659">
    <Connections />
  </Node>
  <Node name="Terokkarzuflucht, Talador" continent="1116" x="2158.65" y="1634.47" z="131.817">
    <Connections />
  </Node>
  <Node name="Das Draakorium, Schattenmondtal" continent="1116" x="128.569" y="-1555.75" z="31.4826">
    <Connections>
      <Connection name="Mondsturz, Schattenmondtal" />
    </Connections>
  </Node>
  <Node name="Elodor, Schattenmondtal" continent="1116" x="1240.2" y="-1666.43" z="44.8835">
    <Connections>
      <Connection name="Mondsturz, Schattenmondtal" />
    </Connections>
  </Node>
  <Node name="Socrethars Klippe, Schattenmondtal" continent="1116" x="-799.674" y="-671.424" z="107.102">
    <Connections />
  </Node>
  <Node name="Südhafen, Spitzen von Arak" continent="1116" x="-1117.45" y="2316.97" z="1.96073">
    <Connections />
  </Node>
  <Node name="Ring der Prüfung, Nagrand" continent="1116" x="3040.78" y="4783.08" z="128.275">
    <Connections />
  </Node>
  <Node name="Thron der Elemente, Nagrand" continent="1116" x="3918.79" y="5131.45" z="62.728">
    <Connections />
  </Node>
  <Node name="Telaaristation, Nagrand" continent="1116" x="2594.25" y="5700.63" z="100.536">
    <Connections />
  </Node>
  <Node name="Yrels Wacht, Nagrand" continent="1116" x="3384.17" y="5755.58" z="39.1851">
    <Connections />
  </Node>
  <Node name="Terokkversteck, Spitzen von Arak" continent="1116" x="-398.988" y="1880.12" z="51.2684">
    <Connections />
  </Node>
  <Node name="Klauenwacht, Spitzen von Arak" continent="1116" x="-335.451" y="926.622" z="75.2153">
    <Connections />
  </Node>
  <Node name="Werkstatt Quetschpfeif, Spitzen von Arak" continent="1116" x="-1579.14" y="993.09" z="8.08963">
    <Connections />
  </Node>
  <Node name="Bastionsklippe, Gorgrond" continent="1116" x="4552.27" y="1274.56" z="144.928">
    <Connections />
  </Node>
  <Node name="Apexisausgrabung, Spitzen von Arak" continent="1116" x="387.542" y="2442.73" z="19.3169">
    <Connections />
  </Node>
  <Node name="Krähenwinkel, Spitzen von Arak" continent="1116" x="128.615" y="1544.63" z="-1.72825">
    <Connections />
  </Node>
  <Node name="Wildwuchsbett, Gorgrond" continent="1116" x="6456.1" y="-174.755" z="120.071">
    <Connections>
      <Connection name="Mondsturz, Schattenmondtal" />
    </Connections>
  </Node>
  <Node name="Hochpass, Gorgrond" continent="1116" x="6352.58" y="746.234" z="116.163">
    <Connections>
      <Connection name="Mondsturz, Schattenmondtal" />
    </Connections>
  </Node>
  <Node name="Brecherkuppe, Gorgrond" continent="1116" x="6593.43" y="1316.04" z="64.6343">
    <Connections />
  </Node>
  <Node name="Tiefwurz, Gorgrond" continent="1116" x="5412.85" y="1271.05" z="101.89">
    <Connections />
  </Node>
  <Node name="Eisendocks, Gorgrond" continent="1116" x="8486.15" y="1544.24" z="78.8754">
    <Connections />
  </Node>
  <Node name="Eisernes Belagerungswerk, Frostfeuergrat" continent="1116" x="5724.26" y="2163.64" z="157.575">
    <Connections />
  </Node>
  <Node name="Nachtflutnest, Schattenmondtal" continent="1116" x="-974.125" y="-1739.3" z="2.99791">
    <Connections />
  </Node>
  <Node name="Horizontklippe, Gorgrond" continent="1116" x="7596.2" y="1829.05" z="79.0772">
    <Connections />
  </Node>
  <Node name="Hof der Ruhe, Schattenmondtal" continent="1116" x="407.042" y="-2449.73" z="99.2637">
    <Connections />
  </Node>
  <Node name="Tempel von Karabor, Schattenmondtal" continent="1116" x="405.788" y="-2448.75" z="99.2643">
    <Connections />
  </Node>
  <Node name="Die Immergrüne Wildnis, Gorgrond" continent="1116" x="7093.6" y="404.74" z="112.001">
    <Connections />
  </Node>
  <Node name="Akeetas Hütte, Schattenmondtal" continent="1116" x="676.424" y="701.439" z="113.96">
    <Connections />
  </Node>
  <Node name="Rilzits Stützpunkt, Nagrand" continent="1116" x="3761.26" y="6430.15" z="21.6669">
    <Connections />
  </Node>
  <Node name="Niveks Aussichtspunkt, Nagrand" continent="1116" x="2053.66" y="6507.39" z="32.264">
    <Connections />
  </Node>
  <Node name="Joz' Rylaks, Nagrand" continent="1116" x="3676.04" y="5776.19" z="45.4013">
    <Connections />
  </Node>
  <Node name="Die Immergrüne Aussicht, Gorgrond" continent="1116" x="8018.09" y="-560.49" z="154.967">
    <Connections />
  </Node>
</FlightNodes>