<HBProfile> <!-- Welcome to Skinning by Bojack -->

	<GrindArea>
		<Name>Bojack's Skinning 1.0</Name>
		
		<TargetMinLevel>90</TargetMinLevel>
		<TargetMaxLevel>100</TargetMaxLevel>
		
		<MinDurability>0.2</MinDurability>
		<MinFreeBagSlots>3</MinFreeBagSlots>
			
			<SellGrey>True</SellGrey>
			<SellWhite>True</SellWhite>
			<SellGreen>False</SellGreen>
			<SellBlue>False</SellBlue>
	
	<Vendors>
		<Vendor Name="Sumi" Entry="82343" Type="Repair" X="3228.321" Y="4625.069" Z="145.0777" />
	</Vendors>

	<Mailboxes>
		<GameObject Name="Mailbox" Entry="232023" X="3207.915" Y="4604.341" Z="143.1709" />
	</Mailboxes>


		<Factions> 2753 16 2000</Factions>
		
		<LootRadius>40</LootRadius>
		<MaxDistance>40</MaxDistance>
		
	<AvoidMobs>
		<Mob Name="Flinthide" Entry="83483" />
	</AvoidMobs>
	
		<RandomizeHotspots>False</RandomizeHotspots>
		
			<Hotspots>
              		<Hotspot X="3082.376" Y="5171.167" Z="90.44985" />
					<Hotspot X="3135.293" Y="5135.886" Z="95.85281" />
					<Hotspot X="3167.657" Y="5097.958" Z="93.05484" />
					<Hotspot X="3147.591" Y="5036.069" Z="88.73089" />
					<Hotspot X="3191.802" Y="4973.552" Z="91.26651" />
					<Hotspot X="3261.161" Y="4947.558" Z="109.1478" />
					<Hotspot X="3337.782" Y="5064.746" Z="90.87759" />
					<Hotspot X="3347.901" Y="5154.602" Z="77.93768" />
					<Hotspot X="3320.038" Y="5247.672" Z="70.41673" />
					<Hotspot X="3243.283" Y="5246.796" Z="86.67567" />
					<Hotspot X="3151.998" Y="5247.136" Z="88.77701" />
					<Hotspot X="3103.428" Y="5239.29" Z="86.005" />
			</Hotspots>
			
	</GrindArea>
	
	</HBProfile>